{"wallet_name":"IIAgent","coldkey":"5GgRojEFh5aCFNLKuSWb6WtrM5nBDB6GrRpqaqreBLcg4e7L","hotkey":"5FsKhptDoRXLdfmTrx15US1imkeuzGnbcPWx1k887DiDRJu9","network":"finney","balance_tao":null,"hotkey_balance_tao":null,"bot_phase":"LIVE","live":true,"yield_maximizer_live":true,"error":"Generic error: Failed to get coldkeypub: FileNotFound(\"Keyfile at: /root/.bittensor/wallets/IIAgent/coldkeypub.txt does not exist.\")","tao_price_usd":257.0,"balance_usd":null,"timestamp":"2026-04-14T20:47:35.064006+00:00"}